dj_check_constraint_validation/__init__.py
dj_check_constraint_validation/apps.py
dj_check_constraint_validation/core.py
dj_check_constraint_validation/forms.py
dj_check_constraint_validation-0.1.0.dist-info/LICENSE
dj_check_constraint_validation-0.1.0.dist-info/WHEEL
dj_check_constraint_validation-0.1.0.dist-info/METADATA
dj_check_constraint_validation-0.1.0.dist-info/RECORD
